metador/__init__.py
metador-0.0.1.dist-info/WHEEL
metador-0.0.1.dist-info/METADATA
metador-0.0.1.dist-info/RECORD
